wcgw/__init__.py
wcgw/types_.py
wcgw/client/__init__.py
wcgw/client/__main__.py
wcgw/client/anthropic_client.py
wcgw/client/cli.py
wcgw/client/common.py
wcgw/client/computer_use.py
wcgw/client/diff-instructions.txt
wcgw/client/memory.py
wcgw/client/modes.py
wcgw/client/openai_client.py
wcgw/client/openai_utils.py
wcgw/client/sys_utils.py
wcgw/client/tools.py
wcgw/client/file_ops/diff_edit.py
wcgw/client/file_ops/search_replace.py
wcgw/client/mcp_server/Readme.md
wcgw/client/mcp_server/__init__.py
wcgw/client/mcp_server/server.py
wcgw/client/repo_ops/display_tree.py
wcgw/client/repo_ops/path_prob.py
wcgw/client/repo_ops/paths_model.vocab
wcgw/client/repo_ops/paths_tokens.model
wcgw/client/repo_ops/repo_context.py
wcgw/relay/serve.py
wcgw/relay/static/privacy.txt
mcp_wcgw/__init__.py
mcp_wcgw/py.typed
mcp_wcgw/types.py
mcp_wcgw/client/__init__.py
mcp_wcgw/client/__main__.py
mcp_wcgw/client/session.py
mcp_wcgw/client/sse.py
mcp_wcgw/client/stdio.py
mcp_wcgw/server/__init__.py
mcp_wcgw/server/__main__.py
mcp_wcgw/server/models.py
mcp_wcgw/server/session.py
mcp_wcgw/server/sse.py
mcp_wcgw/server/stdio.py
mcp_wcgw/server/websocket.py
mcp_wcgw/shared/__init__.py
mcp_wcgw/shared/context.py
mcp_wcgw/shared/exceptions.py
mcp_wcgw/shared/memory.py
mcp_wcgw/shared/progress.py
mcp_wcgw/shared/session.py
mcp_wcgw/shared/version.py
wcgw_linux_compatible_fork-2.8.2.dist-info/METADATA
wcgw_linux_compatible_fork-2.8.2.dist-info/WHEEL
wcgw_linux_compatible_fork-2.8.2.dist-info/entry_points.txt
wcgw_linux_compatible_fork-2.8.2.dist-info/licenses/LICENSE
wcgw_linux_compatible_fork-2.8.2.dist-info/RECORD
