Metadata-Version: 2.4
Name: wcgw-linux-compatible-fork
Version: 2.8.2
Summary: Shell and coding agent on claude and chatgpt
Project-URL: Homepage, https://github.com/rusiaaman/wcgw
Author-email: Aman Rusia <gapypi@arcfu.com>
License-File: LICENSE
Requires-Python: <3.13,>=3.11
Requires-Dist: anthropic>=0.39.0
Requires-Dist: fastapi>=0.115.0
Requires-Dist: openai>=1.46.0
Requires-Dist: petname>=2.6
Requires-Dist: pexpect>=4.9.0
Requires-Dist: pydantic>=2.9.2
Requires-Dist: pygit2>=1.16.0
Requires-Dist: pyte>=0.8.2
Requires-Dist: python-dotenv>=1.0.1
Requires-Dist: rich>=13.8.1
Requires-Dist: semantic-version>=2.10.0
Requires-Dist: shell>=1.0.1
Requires-Dist: syntax-checker==0.2.10
Requires-Dist: tokenizers>=0.21.0
Requires-Dist: toml>=0.10.2
Requires-Dist: typer>=0.12.5
Requires-Dist: types-pexpect>=4.9.0.20240806
Requires-Dist: uvicorn>=0.31.0
Requires-Dist: websockets>=13.1
